__init__.py
config_molmo.py
image_preprocessing_molmo.py
modeling_molmo.py
preprocessing_molmo.py
transformers_module-0.1.0.dist-info/METADATA
transformers_module-0.1.0.dist-info/WHEEL
transformers_module-0.1.0.dist-info/top_level.txt
transformers_module-0.1.0.dist-info/RECORD
